{
  "date": "2026-06-23",
  "caption": "\ud83d\udcca Market recap \u2014 2026-06-23\n\nS&P 500: 7,377.84 (-1.27%)\nNasdaq: 25,656.36 (-1.95%)\nDow Jones: 51,694.26 (-0.04%)\nSectors: Consumer Staples led (+1.86%), Technology lagged (-3.93%).\n\nBitcoin -2.65% \u00b7 Ethereum -4.04%\n\nBiggest odds move: us recession called in 2026 now 12% (+2 vs. yesterday) \u2014 Kalshi.\n\nNot financial advice. For educational purposes only.\n\n#stockmarket #investing #sp500 #nasdaq #crypto",
  "cards": [
    "recap",
    "heatmap",
    "odds"
  ],
  "alt": {
    "recap": "The Print market recap, Jun 23: S&P 500 -1.3%, Nasdaq -1.9%, Dow Jones -0.0%, plus Bitcoin -2.6% and sectors.",
    "heatmap": "The Print sector heatmap, Jun 23: Consumer Staples led +1.9%, Technology lagged -3.9%, across 11 S&P 500 sectors.",
    "odds": "The Print market-implied odds from Kalshi, Jun 23: Core CPI tops 2.8% (YoY) 42%, CPI tops 3.8% (YoY) 34%, and more."
  },
  "image_urls": [
    "https://raw.githubusercontent.com/likethebean17/theprint-cdn/main/theprint/2026-06-23/01-recap.png",
    "https://raw.githubusercontent.com/likethebean17/theprint-cdn/main/theprint/2026-06-23/02-heatmap.png",
    "https://raw.githubusercontent.com/likethebean17/theprint-cdn/main/theprint/2026-06-23/03-odds.png"
  ],
  "generated_at": "2026-06-23T19:24:17+00:00"
}